qlikconnect/__init__.py
qlikconnect/qlikconnect.py
qlikconnect-1.0.2.dist-info/METADATA
qlikconnect-1.0.2.dist-info/WHEEL
qlikconnect-1.0.2.dist-info/top_level.txt
qlikconnect-1.0.2.dist-info/RECORD
