Metadata-Version: 2.1
Name: qlikconnect
Version: 1.0.2
Summary: A Python library to interact with Qliksense.
Home-page: https://github.com/001ayushdabral/qlikconnect
Author: Ayush Dabral
Author-email: ayushdabral88@gmail.com
License: UNKNOWN
Keywords: qlik,qliksense,sense,qlikconnect
Platform: UNKNOWN
Classifier: Programming Language :: Python :: 3
Classifier: License :: OSI Approved :: MIT License
Classifier: Operating System :: OS Independent
Requires-Dist: websocket-client
